dictok/__init__.py
dictok/dictok.py
dictok-0.0.5.dist-info/LICENSE
dictok-0.0.5.dist-info/METADATA
dictok-0.0.5.dist-info/WHEEL
dictok-0.0.5.dist-info/top_level.txt
dictok-0.0.5.dist-info/RECORD
