Metadata-Version: 2.1
Name: dictok
Version: 0.0.5
Summary: A dictionary-based tokenizer.
Home-page: https://github.com/pypa/dictok
Author: Samuel Frontull
Author-email: samuelfrontull@gmail.com
Project-URL: Bug Tracker, https://github.com/pypa/dictok/issues
Classifier: Programming Language :: Python :: 3
Classifier: License :: OSI Approved :: MIT License
Classifier: Operating System :: OS Independent
Requires-Python: >=3.6
License-File: LICENSE
